{
  "byCompany": [
    {
      "label": "Oracle",
      "count": 441
    },
    {
      "label": "Larsen & Toubro",
      "count": 142
    },
    {
      "label": "Accenture services Pvt Ltd",
      "count": 112
    },
    {
      "label": "AlgoSec",
      "count": 85
    },
    {
      "label": "EY",
      "count": 74
    },
    {
      "label": "PwC Acceleration Center India",
      "count": 74
    },
    {
      "label": "Accenture in India",
      "count": 73
    },
    {
      "label": "Uplers",
      "count": 72
    },
    {
      "label": "Infosys",
      "count": 71
    },
    {
      "label": "Walmart Global Tech India",
      "count": 62
    },
    {
      "label": "Amazon",
      "count": 59
    },
    {
      "label": "PwC India",
      "count": 58
    },
    {
      "label": "EXL",
      "count": 53
    },
    {
      "label": "Tata Consultancy Services",
      "count": 36
    },
    {
      "label": "IBM",
      "count": 33
    },
    {
      "label": "LIXIL",
      "count": 31
    },
    {
      "label": "Birlasoft",
      "count": 31
    },
    {
      "label": "Capgemini",
      "count": 31
    },
    {
      "label": "Siemens",
      "count": 28
    },
    {
      "label": "eBay",
      "count": 26
    }
  ],
  "byLocation": [
    {
      "label": "Bengaluru, Karnataka, India",
      "count": 1373
    },
    {
      "label": "Hyderabad, Telangana, India",
      "count": 484
    },
    {
      "label": "Pune, Maharashtra, India",
      "count": 421
    },
    {
      "label": "Chennai, Tamil Nadu, India",
      "count": 269
    },
    {
      "label": "Gurugram, Haryana, India",
      "count": 184
    },
    {
      "label": "Noida, Uttar Pradesh, India",
      "count": 175
    },
    {
      "label": "Mumbai, Maharashtra, India",
      "count": 174
    },
    {
      "label": "India",
      "count": 155
    },
    {
      "label": "Bengaluru East, Karnataka, India",
      "count": 139
    },
    {
      "label": "Mumbai Metropolitan Region",
      "count": 119
    }
  ],
  "byRoleType": [
    {
      "label": "SoftwareQA",
      "count": 1212
    },
    {
      "label": "SoftwareDEV",
      "count": 1158
    },
    {
      "label": "Management",
      "count": 906
    },
    {
      "label": "DevOps/SRE",
      "count": 454
    },
    {
      "label": "ML/AI",
      "count": 427
    },
    {
      "label": "—",
      "count": 326
    },
    {
      "label": "HardwareQA",
      "count": 253
    },
    {
      "label": "PharmaQA",
      "count": 90
    },
    {
      "label": "DataEngg",
      "count": 59
    },
    {
      "label": "RPA",
      "count": 17
    },
    {
      "label": "Security",
      "count": 9
    },
    {
      "label": "DBA",
      "count": 3
    }
  ],
  "techVsRole": {
    "SoftwareQA": {
      "totalJobs": 1212,
      "techs": [
        {
          "label": "Java",
          "count": 435
        },
        {
          "label": "Git",
          "count": 399
        },
        {
          "label": "CI_CD",
          "count": 390
        },
        {
          "label": "Automation_Tools",
          "count": 668
        },
        {
          "label": "MobileTest",
          "count": 115
        },
        {
          "label": "APITest",
          "count": 354
        },
        {
          "label": "Python",
          "count": 339
        },
        {
          "label": "Azure_Cloud",
          "count": 247
        },
        {
          "label": "PerfTest",
          "count": 190
        },
        {
          "label": "Agile_Scrum",
          "count": 627
        },
        {
          "label": "Agile_Tools",
          "count": 273
        },
        {
          "label": "ETL",
          "count": 51
        },
        {
          "label": "Containerization",
          "count": 144
        },
        {
          "label": "Compliance",
          "count": 19
        },
        {
          "label": "RDBMS",
          "count": 59
        },
        {
          "label": "AWS_Cloud",
          "count": 251
        },
        {
          "label": "ManualTest",
          "count": 366
        },
        {
          "label": "TypeScript",
          "count": 116
        },
        {
          "label": "Embedded_Tools",
          "count": 12
        },
        {
          "label": "Cert_ISTQB",
          "count": 62
        },
        {
          "label": "Google_Cloud",
          "count": 120
        },
        {
          "label": "Linux_Unix",
          "count": 86
        },
        {
          "label": "Windows",
          "count": 29
        },
        {
          "label": "NoSQL_DB",
          "count": 44
        },
        {
          "label": "DataStreaming",
          "count": 22
        },
        {
          "label": "JavaScript",
          "count": 269
        },
        {
          "label": "MachineLearning",
          "count": 68
        },
        {
          "label": "Embedded_RTOS",
          "count": 55
        },
        {
          "label": "GenAI",
          "count": 46
        },
        {
          "label": "React",
          "count": 53
        },
        {
          "label": "Tailwind",
          "count": 10
        },
        {
          "label": "RPA_Tools",
          "count": 13
        },
        {
          "label": "HardwareTest",
          "count": 2
        },
        {
          "label": "GraphQL",
          "count": 22
        },
        {
          "label": "Go",
          "count": 56
        },
        {
          "label": "DB_Mgmt",
          "count": 5
        },
        {
          "label": "Angular",
          "count": 26
        },
        {
          "label": "Vue",
          "count": 8
        },
        {
          "label": "NodeJS",
          "count": 34
        },
        {
          "label": "Spring",
          "count": 12
        },
        {
          "label": "Django",
          "count": 1
        },
        {
          "label": "IaC",
          "count": 17
        },
        {
          "label": "Observability",
          "count": 42
        },
        {
          "label": "AppSec",
          "count": 15
        },
        {
          "label": "DataOrchestration",
          "count": 14
        },
        {
          "label": "DataWarehouse",
          "count": 33
        },
        {
          "label": "NetworkSec",
          "count": 12
        },
        {
          "label": "IdentitySec",
          "count": 10
        },
        {
          "label": "MacOS",
          "count": 4
        },
        {
          "label": "Swift",
          "count": 18
        },
        {
          "label": "Cert_Oracle",
          "count": 2
        },
        {
          "label": "BigData",
          "count": 19
        },
        {
          "label": "Cert_Cisco",
          "count": 4
        },
        {
          "label": "Cert_LinuxFoundation",
          "count": 2
        },
        {
          "label": "SRE",
          "count": 12
        },
        {
          "label": "Cert_AWS",
          "count": 4
        },
        {
          "label": "C#",
          "count": 5
        },
        {
          "label": "DataScience",
          "count": 3
        },
        {
          "label": "DeepLearning",
          "count": 7
        },
        {
          "label": "FastAPI",
          "count": 4
        },
        {
          "label": "Rust",
          "count": 1
        },
        {
          "label": "Cert_PMI",
          "count": 2
        },
        {
          "label": "Cert_ISC2",
          "count": 3
        },
        {
          "label": "Cert_ISACA",
          "count": 2
        },
        {
          "label": "Cert_ScrumAlliance",
          "count": 9
        },
        {
          "label": "Flutter",
          "count": 3
        },
        {
          "label": "Kotlin",
          "count": 2
        },
        {
          "label": "Cert_Salesforce",
          "count": 5
        },
        {
          "label": "Cert_OffSec",
          "count": 1
        }
      ]
    },
    "Management": {
      "totalJobs": 906,
      "techs": [
        {
          "label": "Agile_Scrum",
          "count": 192
        },
        {
          "label": "Go",
          "count": 69
        },
        {
          "label": "Python",
          "count": 28
        },
        {
          "label": "Java",
          "count": 30
        },
        {
          "label": "AWS_Cloud",
          "count": 33
        },
        {
          "label": "NetworkSec",
          "count": 7
        },
        {
          "label": "Cert_ScrumAlliance",
          "count": 8
        },
        {
          "label": "MachineLearning",
          "count": 36
        },
        {
          "label": "Cert_PMI",
          "count": 23
        },
        {
          "label": "JavaScript",
          "count": 19
        },
        {
          "label": "TypeScript",
          "count": 7
        },
        {
          "label": "React",
          "count": 17
        },
        {
          "label": "Angular",
          "count": 8
        },
        {
          "label": "Vue",
          "count": 3
        },
        {
          "label": "NodeJS",
          "count": 5
        },
        {
          "label": "Git",
          "count": 20
        },
        {
          "label": "SRE",
          "count": 2
        },
        {
          "label": "Agile_Tools",
          "count": 37
        },
        {
          "label": "Compliance",
          "count": 21
        },
        {
          "label": "ManualTest",
          "count": 3
        },
        {
          "label": "Cert_ISACA",
          "count": 9
        },
        {
          "label": "Azure_Cloud",
          "count": 28
        },
        {
          "label": "Google_Cloud",
          "count": 20
        },
        {
          "label": "Linux_Unix",
          "count": 5
        },
        {
          "label": "Swift",
          "count": 1
        },
        {
          "label": "GraphQL",
          "count": 4
        },
        {
          "label": "DataStreaming",
          "count": 4
        },
        {
          "label": "Containerization",
          "count": 16
        },
        {
          "label": "DB_Mgmt",
          "count": 2
        },
        {
          "label": "DataWarehouse",
          "count": 5
        },
        {
          "label": "C++",
          "count": 2
        },
        {
          "label": "Spring",
          "count": 3
        },
        {
          "label": "IdentitySec",
          "count": 8
        },
        {
          "label": "Windows",
          "count": 10
        },
        {
          "label": "RDBMS",
          "count": 11
        },
        {
          "label": "NoSQL_DB",
          "count": 7
        },
        {
          "label": "GenAI",
          "count": 16
        },
        {
          "label": "CI_CD",
          "count": 10
        },
        {
          "label": "RPA_Tools",
          "count": 3
        },
        {
          "label": "Automation_Tools",
          "count": 3
        },
        {
          "label": "IaC",
          "count": 1
        },
        {
          "label": "HardwareTest",
          "count": 3
        },
        {
          "label": "C#",
          "count": 1
        },
        {
          "label": "BigData",
          "count": 3
        },
        {
          "label": "Instrumentation",
          "count": 1
        },
        {
          "label": "Flutter",
          "count": 1
        },
        {
          "label": "MacOS",
          "count": 3
        },
        {
          "label": "ETL",
          "count": 4
        },
        {
          "label": "Cert_ScrumOrg",
          "count": 2
        },
        {
          "label": "AppSec",
          "count": 1
        },
        {
          "label": "Tailwind",
          "count": 1
        },
        {
          "label": "Cert_LinuxFoundation",
          "count": 1
        },
        {
          "label": "Observability",
          "count": 2
        },
        {
          "label": "Cert_ISC2",
          "count": 5
        },
        {
          "label": "APITest",
          "count": 1
        },
        {
          "label": "Cert_AWS",
          "count": 1
        },
        {
          "label": "Django",
          "count": 1
        },
        {
          "label": "Cert_Azure",
          "count": 1
        },
        {
          "label": "Cert_Cisco",
          "count": 1
        },
        {
          "label": "Cert_CompTIA",
          "count": 1
        }
      ]
    },
    "ML/AI": {
      "totalJobs": 427,
      "techs": [
        {
          "label": "MachineLearning",
          "count": 398
        },
        {
          "label": "DeepLearning",
          "count": 240
        },
        {
          "label": "GenAI",
          "count": 270
        },
        {
          "label": "Agile_Scrum",
          "count": 71
        },
        {
          "label": "Python",
          "count": 292
        },
        {
          "label": "FastAPI",
          "count": 58
        },
        {
          "label": "DataWarehouse",
          "count": 38
        },
        {
          "label": "AWS_Cloud",
          "count": 157
        },
        {
          "label": "Azure_Cloud",
          "count": 162
        },
        {
          "label": "Google_Cloud",
          "count": 120
        },
        {
          "label": "Containerization",
          "count": 124
        },
        {
          "label": "RDBMS",
          "count": 34
        },
        {
          "label": "Git",
          "count": 65
        },
        {
          "label": "BigData",
          "count": 72
        },
        {
          "label": "Go",
          "count": 24
        },
        {
          "label": "DataStreaming",
          "count": 25
        },
        {
          "label": "IaC",
          "count": 10
        },
        {
          "label": "DataScience",
          "count": 63
        },
        {
          "label": "Java",
          "count": 92
        },
        {
          "label": "Observability",
          "count": 27
        },
        {
          "label": "Automation_Tools",
          "count": 28
        },
        {
          "label": "NoSQL_DB",
          "count": 35
        },
        {
          "label": "Compliance",
          "count": 7
        },
        {
          "label": "Cert_AWS",
          "count": 5
        },
        {
          "label": "Django",
          "count": 11
        },
        {
          "label": "Agile_Tools",
          "count": 28
        },
        {
          "label": "DataOrchestration",
          "count": 24
        },
        {
          "label": "IdentitySec",
          "count": 8
        },
        {
          "label": "JavaScript",
          "count": 22
        },
        {
          "label": "SRE",
          "count": 3
        },
        {
          "label": "CI_CD",
          "count": 23
        },
        {
          "label": "Linux_Unix",
          "count": 23
        },
        {
          "label": "Windows",
          "count": 5
        },
        {
          "label": "ETL",
          "count": 15
        },
        {
          "label": "React",
          "count": 18
        },
        {
          "label": "Spring",
          "count": 10
        },
        {
          "label": "GraphQL",
          "count": 7
        },
        {
          "label": "NodeJS",
          "count": 12
        },
        {
          "label": "Angular",
          "count": 12
        },
        {
          "label": "Vue",
          "count": 1
        },
        {
          "label": "DB_Mgmt",
          "count": 8
        },
        {
          "label": "APITest",
          "count": 2
        },
        {
          "label": "Cert_Azure",
          "count": 1
        },
        {
          "label": "Cert_LinuxFoundation",
          "count": 1
        },
        {
          "label": "TypeScript",
          "count": 6
        },
        {
          "label": "C++",
          "count": 1
        },
        {
          "label": "Rust",
          "count": 2
        },
        {
          "label": "AppSec",
          "count": 1
        },
        {
          "label": "NetworkSec",
          "count": 1
        },
        {
          "label": "Cert_OffSec",
          "count": 1
        },
        {
          "label": "Kotlin",
          "count": 3
        },
        {
          "label": "RPA_Tools",
          "count": 5
        },
        {
          "label": "Swift",
          "count": 1
        }
      ]
    },
    "RPA": {
      "totalJobs": 17,
      "techs": [
        {
          "label": "RPA_Tools",
          "count": 13
        },
        {
          "label": "Go",
          "count": 1
        },
        {
          "label": "Agile_Scrum",
          "count": 6
        },
        {
          "label": "MachineLearning",
          "count": 3
        },
        {
          "label": "Python",
          "count": 4
        },
        {
          "label": "GenAI",
          "count": 2
        },
        {
          "label": "Java",
          "count": 1
        },
        {
          "label": "Linux_Unix",
          "count": 1
        },
        {
          "label": "RDBMS",
          "count": 1
        }
      ]
    },
    "DevOps/SRE": {
      "totalJobs": 454,
      "techs": [
        {
          "label": "Python",
          "count": 227
        },
        {
          "label": "Java",
          "count": 189
        },
        {
          "label": "Spring",
          "count": 20
        },
        {
          "label": "GraphQL",
          "count": 8
        },
        {
          "label": "DataStreaming",
          "count": 42
        },
        {
          "label": "AWS_Cloud",
          "count": 230
        },
        {
          "label": "Azure_Cloud",
          "count": 195
        },
        {
          "label": "Google_Cloud",
          "count": 141
        },
        {
          "label": "Containerization",
          "count": 213
        },
        {
          "label": "BigData",
          "count": 34
        },
        {
          "label": "IaC",
          "count": 134
        },
        {
          "label": "CI_CD",
          "count": 153
        },
        {
          "label": "Linux_Unix",
          "count": 123
        },
        {
          "label": "Go",
          "count": 126
        },
        {
          "label": "Kotlin",
          "count": 15
        },
        {
          "label": "Git",
          "count": 143
        },
        {
          "label": "MachineLearning",
          "count": 88
        },
        {
          "label": "GenAI",
          "count": 53
        },
        {
          "label": "Observability",
          "count": 124
        },
        {
          "label": "SRE",
          "count": 88
        },
        {
          "label": "NetworkSec",
          "count": 21
        },
        {
          "label": "NodeJS",
          "count": 22
        },
        {
          "label": "Agile_Scrum",
          "count": 135
        },
        {
          "label": "Windows",
          "count": 26
        },
        {
          "label": "Agile_Tools",
          "count": 52
        },
        {
          "label": "IdentitySec",
          "count": 38
        },
        {
          "label": "JavaScript",
          "count": 32
        },
        {
          "label": "TypeScript",
          "count": 12
        },
        {
          "label": "RDBMS",
          "count": 49
        },
        {
          "label": "Embedded_Tools",
          "count": 3
        },
        {
          "label": "NoSQL_DB",
          "count": 42
        },
        {
          "label": "Cert_AWS",
          "count": 26
        },
        {
          "label": "DataWarehouse",
          "count": 21
        },
        {
          "label": "Cert_CompTIA",
          "count": 1
        },
        {
          "label": "ETL",
          "count": 23
        },
        {
          "label": "Cert_Azure",
          "count": 4
        },
        {
          "label": "Angular",
          "count": 13
        },
        {
          "label": "Automation_Tools",
          "count": 14
        },
        {
          "label": "FastAPI",
          "count": 9
        },
        {
          "label": "Cert_ScrumAlliance",
          "count": 2
        },
        {
          "label": "Compliance",
          "count": 19
        },
        {
          "label": "PerfTest",
          "count": 4
        },
        {
          "label": "AppSec",
          "count": 16
        },
        {
          "label": "Cert_LinuxFoundation",
          "count": 11
        },
        {
          "label": "C++",
          "count": 1
        },
        {
          "label": "Rust",
          "count": 6
        },
        {
          "label": "DataOrchestration",
          "count": 11
        },
        {
          "label": "React",
          "count": 20
        },
        {
          "label": "Django",
          "count": 5
        },
        {
          "label": "DeepLearning",
          "count": 16
        },
        {
          "label": "MacOS",
          "count": 2
        },
        {
          "label": "Cert_GCP",
          "count": 3
        },
        {
          "label": "Cert_Cisco",
          "count": 2
        },
        {
          "label": "C#",
          "count": 1
        },
        {
          "label": "RPA_Tools",
          "count": 14
        },
        {
          "label": "APITest",
          "count": 7
        },
        {
          "label": "Cert_PMI",
          "count": 4
        },
        {
          "label": "DB_Mgmt",
          "count": 2
        },
        {
          "label": "Swift",
          "count": 1
        },
        {
          "label": "DataScience",
          "count": 4
        },
        {
          "label": "ManualTest",
          "count": 1
        },
        {
          "label": "Cert_ISC2",
          "count": 2
        },
        {
          "label": "Cert_ISACA",
          "count": 2
        },
        {
          "label": "Vue",
          "count": 1
        }
      ]
    },
    "HardwareQA": {
      "totalJobs": 253,
      "techs": [
        {
          "label": "Embedded_Tools",
          "count": 35
        },
        {
          "label": "Agile_Scrum",
          "count": 42
        },
        {
          "label": "NetworkSec",
          "count": 20
        },
        {
          "label": "HardwareTest",
          "count": 17
        },
        {
          "label": "AWS_Cloud",
          "count": 4
        },
        {
          "label": "MachineLearning",
          "count": 7
        },
        {
          "label": "Go",
          "count": 8
        },
        {
          "label": "Python",
          "count": 26
        },
        {
          "label": "Embedded_RTOS",
          "count": 9
        },
        {
          "label": "Agile_Tools",
          "count": 6
        },
        {
          "label": "Git",
          "count": 7
        },
        {
          "label": "Automation_Tools",
          "count": 1
        },
        {
          "label": "Linux_Unix",
          "count": 5
        },
        {
          "label": "GraphQL",
          "count": 1
        },
        {
          "label": "Instrumentation",
          "count": 5
        },
        {
          "label": "Windows",
          "count": 3
        },
        {
          "label": "Java",
          "count": 1
        },
        {
          "label": "DeepLearning",
          "count": 1
        },
        {
          "label": "CI_CD",
          "count": 1
        },
        {
          "label": "NodeJS",
          "count": 2
        },
        {
          "label": "GenAI",
          "count": 1
        },
        {
          "label": "ManualTest",
          "count": 1
        },
        {
          "label": "Cert_ScrumAlliance",
          "count": 1
        },
        {
          "label": "React",
          "count": 1
        },
        {
          "label": "Cert_ScrumOrg",
          "count": 1
        }
      ]
    },
    "SoftwareDEV": {
      "totalJobs": 1158,
      "techs": [
        {
          "label": "JavaScript",
          "count": 401
        },
        {
          "label": "TypeScript",
          "count": 168
        },
        {
          "label": "Java",
          "count": 546
        },
        {
          "label": "Swift",
          "count": 21
        },
        {
          "label": "Kotlin",
          "count": 28
        },
        {
          "label": "React",
          "count": 330
        },
        {
          "label": "Git",
          "count": 365
        },
        {
          "label": "FastAPI",
          "count": 50
        },
        {
          "label": "GenAI",
          "count": 96
        },
        {
          "label": "Python",
          "count": 313
        },
        {
          "label": "Linux_Unix",
          "count": 147
        },
        {
          "label": "GraphQL",
          "count": 103
        },
        {
          "label": "Azure_Cloud",
          "count": 192
        },
        {
          "label": "Containerization",
          "count": 305
        },
        {
          "label": "CI_CD",
          "count": 133
        },
        {
          "label": "Angular",
          "count": 210
        },
        {
          "label": "Vue",
          "count": 68
        },
        {
          "label": "Tailwind",
          "count": 29
        },
        {
          "label": "NodeJS",
          "count": 190
        },
        {
          "label": "DataStreaming",
          "count": 142
        },
        {
          "label": "Observability",
          "count": 59
        },
        {
          "label": "RDBMS",
          "count": 285
        },
        {
          "label": "NoSQL_DB",
          "count": 195
        },
        {
          "label": "Spring",
          "count": 199
        },
        {
          "label": "AWS_Cloud",
          "count": 317
        },
        {
          "label": "Go",
          "count": 146
        },
        {
          "label": "Cert_AWS",
          "count": 17
        },
        {
          "label": "Agile_Scrum",
          "count": 432
        },
        {
          "label": "DB_Mgmt",
          "count": 22
        },
        {
          "label": "C#",
          "count": 11
        },
        {
          "label": "IdentitySec",
          "count": 72
        },
        {
          "label": "MachineLearning",
          "count": 156
        },
        {
          "label": "PerfTest",
          "count": 41
        },
        {
          "label": "Agile_Tools",
          "count": 101
        },
        {
          "label": "Django",
          "count": 54
        },
        {
          "label": "Automation_Tools",
          "count": 109
        },
        {
          "label": "APITest",
          "count": 20
        },
        {
          "label": "Google_Cloud",
          "count": 149
        },
        {
          "label": "BigData",
          "count": 68
        },
        {
          "label": "SRE",
          "count": 6
        },
        {
          "label": "Embedded_Tools",
          "count": 8
        },
        {
          "label": "Embedded_RTOS",
          "count": 6
        },
        {
          "label": "DataWarehouse",
          "count": 45
        },
        {
          "label": "ETL",
          "count": 27
        },
        {
          "label": "IaC",
          "count": 42
        },
        {
          "label": "AppSec",
          "count": 15
        },
        {
          "label": "DataOrchestration",
          "count": 9
        },
        {
          "label": "Compliance",
          "count": 18
        },
        {
          "label": "Cert_Azure",
          "count": 2
        },
        {
          "label": "Cert_Cisco",
          "count": 2
        },
        {
          "label": "Cert_ISC2",
          "count": 2
        },
        {
          "label": "Flutter",
          "count": 20
        },
        {
          "label": "Cert_Oracle",
          "count": 2
        },
        {
          "label": "DeepLearning",
          "count": 18
        },
        {
          "label": "Windows",
          "count": 17
        },
        {
          "label": "MacOS",
          "count": 3
        },
        {
          "label": "Cert_Salesforce",
          "count": 4
        },
        {
          "label": "DataScience",
          "count": 15
        },
        {
          "label": "NetworkSec",
          "count": 9
        },
        {
          "label": "C++",
          "count": 2
        },
        {
          "label": "Rust",
          "count": 3
        },
        {
          "label": "HardwareTest",
          "count": 2
        },
        {
          "label": "ManualTest",
          "count": 2
        },
        {
          "label": "Cert_LinuxFoundation",
          "count": 2
        },
        {
          "label": "MobileTest",
          "count": 1
        },
        {
          "label": "Cert_ScrumAlliance",
          "count": 5
        },
        {
          "label": "RPA_Tools",
          "count": 2
        }
      ]
    },
    "PharmaQA": {
      "totalJobs": 90,
      "techs": [
        {
          "label": "Embedded_Tools",
          "count": 1
        },
        {
          "label": "Python",
          "count": 2
        },
        {
          "label": "Compliance",
          "count": 2
        },
        {
          "label": "Go",
          "count": 4
        },
        {
          "label": "Rust",
          "count": 2
        },
        {
          "label": "Agile_Scrum",
          "count": 15
        },
        {
          "label": "Cert_ScrumAlliance",
          "count": 1
        },
        {
          "label": "NetworkSec",
          "count": 2
        },
        {
          "label": "Cert_PMI",
          "count": 1
        },
        {
          "label": "MachineLearning",
          "count": 1
        },
        {
          "label": "DataWarehouse",
          "count": 1
        },
        {
          "label": "Google_Cloud",
          "count": 1
        },
        {
          "label": "Linux_Unix",
          "count": 1
        }
      ]
    },
    "DataEngg": {
      "totalJobs": 59,
      "techs": [
        {
          "label": "Python",
          "count": 40
        },
        {
          "label": "BigData",
          "count": 24
        },
        {
          "label": "DataWarehouse",
          "count": 39
        },
        {
          "label": "DataScience",
          "count": 2
        },
        {
          "label": "MachineLearning",
          "count": 14
        },
        {
          "label": "DeepLearning",
          "count": 1
        },
        {
          "label": "AWS_Cloud",
          "count": 25
        },
        {
          "label": "Azure_Cloud",
          "count": 30
        },
        {
          "label": "Google_Cloud",
          "count": 13
        },
        {
          "label": "ETL",
          "count": 42
        },
        {
          "label": "RDBMS",
          "count": 14
        },
        {
          "label": "Automation_Tools",
          "count": 3
        },
        {
          "label": "Git",
          "count": 13
        },
        {
          "label": "GenAI",
          "count": 2
        },
        {
          "label": "DB_Mgmt",
          "count": 3
        },
        {
          "label": "Go",
          "count": 6
        },
        {
          "label": "FastAPI",
          "count": 1
        },
        {
          "label": "DataOrchestration",
          "count": 10
        },
        {
          "label": "Containerization",
          "count": 5
        },
        {
          "label": "CI_CD",
          "count": 3
        },
        {
          "label": "Agile_Scrum",
          "count": 15
        },
        {
          "label": "Linux_Unix",
          "count": 8
        },
        {
          "label": "Agile_Tools",
          "count": 6
        },
        {
          "label": "Java",
          "count": 7
        },
        {
          "label": "Cert_PMI",
          "count": 1
        },
        {
          "label": "DataStreaming",
          "count": 6
        },
        {
          "label": "JavaScript",
          "count": 3
        },
        {
          "label": "React",
          "count": 2
        },
        {
          "label": "Angular",
          "count": 2
        },
        {
          "label": "Vue",
          "count": 2
        },
        {
          "label": "IaC",
          "count": 4
        },
        {
          "label": "NoSQL_DB",
          "count": 1
        },
        {
          "label": "ManualTest",
          "count": 1
        },
        {
          "label": "Compliance",
          "count": 2
        },
        {
          "label": "Cert_ISC2",
          "count": 1
        }
      ]
    },
    "DBA": {
      "totalJobs": 3,
      "techs": [
        {
          "label": "Go",
          "count": 1
        }
      ]
    },
    "Security": {
      "totalJobs": 9,
      "techs": [
        {
          "label": "Git",
          "count": 2
        },
        {
          "label": "AWS_Cloud",
          "count": 3
        },
        {
          "label": "Azure_Cloud",
          "count": 2
        },
        {
          "label": "Google_Cloud",
          "count": 2
        },
        {
          "label": "CI_CD",
          "count": 2
        },
        {
          "label": "AppSec",
          "count": 1
        },
        {
          "label": "Agile_Scrum",
          "count": 2
        },
        {
          "label": "Cert_ScrumAlliance",
          "count": 1
        },
        {
          "label": "Python",
          "count": 3
        },
        {
          "label": "Go",
          "count": 2
        },
        {
          "label": "Containerization",
          "count": 2
        },
        {
          "label": "ManualTest",
          "count": 1
        },
        {
          "label": "Linux_Unix",
          "count": 1
        },
        {
          "label": "Windows",
          "count": 1
        },
        {
          "label": "DataWarehouse",
          "count": 1
        },
        {
          "label": "GenAI",
          "count": 1
        },
        {
          "label": "IaC",
          "count": 1
        },
        {
          "label": "Compliance",
          "count": 1
        },
        {
          "label": "Cert_Cisco",
          "count": 1
        }
      ]
    }
  },
  "companyVsExperience": [
    {
      "company": "Oracle",
      "totalJobs": 441,
      "distribution": [
        {
          "range": "0-3 Years",
          "count": 67
        },
        {
          "range": "4-6 Years",
          "count": 117
        },
        {
          "range": "7-9 Years",
          "count": 30
        },
        {
          "range": "10-12 Years",
          "count": 41
        },
        {
          "range": "13-16 Years",
          "count": 2
        },
        {
          "range": "17-20 Years",
          "count": 0
        },
        {
          "range": "21+ Years",
          "count": 0
        }
      ]
    },
    {
      "company": "Larsen & Toubro",
      "totalJobs": 142,
      "distribution": [
        {
          "range": "0-3 Years",
          "count": 1
        },
        {
          "range": "4-6 Years",
          "count": 20
        },
        {
          "range": "7-9 Years",
          "count": 7
        },
        {
          "range": "10-12 Years",
          "count": 13
        },
        {
          "range": "13-16 Years",
          "count": 5
        },
        {
          "range": "17-20 Years",
          "count": 2
        },
        {
          "range": "21+ Years",
          "count": 1
        }
      ]
    },
    {
      "company": "Accenture services Pvt Ltd",
      "totalJobs": 112,
      "distribution": [
        {
          "range": "0-3 Years",
          "count": 46
        },
        {
          "range": "4-6 Years",
          "count": 40
        },
        {
          "range": "7-9 Years",
          "count": 0
        },
        {
          "range": "10-12 Years",
          "count": 2
        },
        {
          "range": "13-16 Years",
          "count": 23
        },
        {
          "range": "17-20 Years",
          "count": 1
        },
        {
          "range": "21+ Years",
          "count": 0
        }
      ]
    },
    {
      "company": "AlgoSec",
      "totalJobs": 85,
      "distribution": [
        {
          "range": "0-3 Years",
          "count": 30
        },
        {
          "range": "4-6 Years",
          "count": 52
        },
        {
          "range": "7-9 Years",
          "count": 0
        },
        {
          "range": "10-12 Years",
          "count": 0
        },
        {
          "range": "13-16 Years",
          "count": 0
        },
        {
          "range": "17-20 Years",
          "count": 0
        },
        {
          "range": "21+ Years",
          "count": 0
        }
      ]
    },
    {
      "company": "EY",
      "totalJobs": 74,
      "distribution": [
        {
          "range": "0-3 Years",
          "count": 13
        },
        {
          "range": "4-6 Years",
          "count": 6
        },
        {
          "range": "7-9 Years",
          "count": 31
        },
        {
          "range": "10-12 Years",
          "count": 11
        },
        {
          "range": "13-16 Years",
          "count": 1
        },
        {
          "range": "17-20 Years",
          "count": 0
        },
        {
          "range": "21+ Years",
          "count": 0
        }
      ]
    },
    {
      "company": "PwC Acceleration Center India",
      "totalJobs": 74,
      "distribution": [
        {
          "range": "0-3 Years",
          "count": 9
        },
        {
          "range": "4-6 Years",
          "count": 33
        },
        {
          "range": "7-9 Years",
          "count": 17
        },
        {
          "range": "10-12 Years",
          "count": 7
        },
        {
          "range": "13-16 Years",
          "count": 0
        },
        {
          "range": "17-20 Years",
          "count": 0
        },
        {
          "range": "21+ Years",
          "count": 0
        }
      ]
    },
    {
      "company": "Accenture in India",
      "totalJobs": 73,
      "distribution": [
        {
          "range": "0-3 Years",
          "count": 46
        },
        {
          "range": "4-6 Years",
          "count": 9
        },
        {
          "range": "7-9 Years",
          "count": 1
        },
        {
          "range": "10-12 Years",
          "count": 3
        },
        {
          "range": "13-16 Years",
          "count": 13
        },
        {
          "range": "17-20 Years",
          "count": 0
        },
        {
          "range": "21+ Years",
          "count": 0
        }
      ]
    },
    {
      "company": "Uplers",
      "totalJobs": 72,
      "distribution": [
        {
          "range": "0-3 Years",
          "count": 11
        },
        {
          "range": "4-6 Years",
          "count": 58
        },
        {
          "range": "7-9 Years",
          "count": 1
        },
        {
          "range": "10-12 Years",
          "count": 0
        },
        {
          "range": "13-16 Years",
          "count": 0
        },
        {
          "range": "17-20 Years",
          "count": 0
        },
        {
          "range": "21+ Years",
          "count": 0
        }
      ]
    },
    {
      "company": "Infosys",
      "totalJobs": 71,
      "distribution": [
        {
          "range": "0-3 Years",
          "count": 2
        },
        {
          "range": "4-6 Years",
          "count": 17
        },
        {
          "range": "7-9 Years",
          "count": 8
        },
        {
          "range": "10-12 Years",
          "count": 1
        },
        {
          "range": "13-16 Years",
          "count": 0
        },
        {
          "range": "17-20 Years",
          "count": 0
        },
        {
          "range": "21+ Years",
          "count": 0
        }
      ]
    },
    {
      "company": "Walmart Global Tech India",
      "totalJobs": 62,
      "distribution": [
        {
          "range": "0-3 Years",
          "count": 2
        },
        {
          "range": "4-6 Years",
          "count": 33
        },
        {
          "range": "7-9 Years",
          "count": 9
        },
        {
          "range": "10-12 Years",
          "count": 14
        },
        {
          "range": "13-16 Years",
          "count": 4
        },
        {
          "range": "17-20 Years",
          "count": 0
        },
        {
          "range": "21+ Years",
          "count": 0
        }
      ]
    },
    {
      "company": "Amazon",
      "totalJobs": 59,
      "distribution": [
        {
          "range": "0-3 Years",
          "count": 40
        },
        {
          "range": "4-6 Years",
          "count": 6
        },
        {
          "range": "7-9 Years",
          "count": 3
        },
        {
          "range": "10-12 Years",
          "count": 0
        },
        {
          "range": "13-16 Years",
          "count": 0
        },
        {
          "range": "17-20 Years",
          "count": 0
        },
        {
          "range": "21+ Years",
          "count": 0
        }
      ]
    },
    {
      "company": "PwC India",
      "totalJobs": 58,
      "distribution": [
        {
          "range": "0-3 Years",
          "count": 1
        },
        {
          "range": "4-6 Years",
          "count": 27
        },
        {
          "range": "7-9 Years",
          "count": 18
        },
        {
          "range": "10-12 Years",
          "count": 3
        },
        {
          "range": "13-16 Years",
          "count": 1
        },
        {
          "range": "17-20 Years",
          "count": 1
        },
        {
          "range": "21+ Years",
          "count": 0
        }
      ]
    },
    {
      "company": "EXL",
      "totalJobs": 53,
      "distribution": [
        {
          "range": "0-3 Years",
          "count": 4
        },
        {
          "range": "4-6 Years",
          "count": 13
        },
        {
          "range": "7-9 Years",
          "count": 2
        },
        {
          "range": "10-12 Years",
          "count": 1
        },
        {
          "range": "13-16 Years",
          "count": 0
        },
        {
          "range": "17-20 Years",
          "count": 0
        },
        {
          "range": "21+ Years",
          "count": 0
        }
      ]
    },
    {
      "company": "Tata Consultancy Services",
      "totalJobs": 36,
      "distribution": [
        {
          "range": "0-3 Years",
          "count": 1
        },
        {
          "range": "4-6 Years",
          "count": 4
        },
        {
          "range": "7-9 Years",
          "count": 20
        },
        {
          "range": "10-12 Years",
          "count": 7
        },
        {
          "range": "13-16 Years",
          "count": 1
        },
        {
          "range": "17-20 Years",
          "count": 0
        },
        {
          "range": "21+ Years",
          "count": 0
        }
      ]
    },
    {
      "company": "IBM",
      "totalJobs": 33,
      "distribution": [
        {
          "range": "0-3 Years",
          "count": 3
        },
        {
          "range": "4-6 Years",
          "count": 18
        },
        {
          "range": "7-9 Years",
          "count": 1
        },
        {
          "range": "10-12 Years",
          "count": 1
        },
        {
          "range": "13-16 Years",
          "count": 1
        },
        {
          "range": "17-20 Years",
          "count": 0
        },
        {
          "range": "21+ Years",
          "count": 0
        }
      ]
    },
    {
      "company": "LIXIL",
      "totalJobs": 31,
      "distribution": [
        {
          "range": "0-3 Years",
          "count": 0
        },
        {
          "range": "4-6 Years",
          "count": 27
        },
        {
          "range": "7-9 Years",
          "count": 0
        },
        {
          "range": "10-12 Years",
          "count": 1
        },
        {
          "range": "13-16 Years",
          "count": 0
        },
        {
          "range": "17-20 Years",
          "count": 0
        },
        {
          "range": "21+ Years",
          "count": 0
        }
      ]
    },
    {
      "company": "Birlasoft",
      "totalJobs": 31,
      "distribution": [
        {
          "range": "0-3 Years",
          "count": 1
        },
        {
          "range": "4-6 Years",
          "count": 10
        },
        {
          "range": "7-9 Years",
          "count": 10
        },
        {
          "range": "10-12 Years",
          "count": 4
        },
        {
          "range": "13-16 Years",
          "count": 3
        },
        {
          "range": "17-20 Years",
          "count": 0
        },
        {
          "range": "21+ Years",
          "count": 0
        }
      ]
    },
    {
      "company": "Capgemini",
      "totalJobs": 31,
      "distribution": [
        {
          "range": "0-3 Years",
          "count": 2
        },
        {
          "range": "4-6 Years",
          "count": 5
        },
        {
          "range": "7-9 Years",
          "count": 3
        },
        {
          "range": "10-12 Years",
          "count": 1
        },
        {
          "range": "13-16 Years",
          "count": 0
        },
        {
          "range": "17-20 Years",
          "count": 0
        },
        {
          "range": "21+ Years",
          "count": 0
        }
      ]
    },
    {
      "company": "Siemens",
      "totalJobs": 28,
      "distribution": [
        {
          "range": "0-3 Years",
          "count": 4
        },
        {
          "range": "4-6 Years",
          "count": 7
        },
        {
          "range": "7-9 Years",
          "count": 3
        },
        {
          "range": "10-12 Years",
          "count": 2
        },
        {
          "range": "13-16 Years",
          "count": 0
        },
        {
          "range": "17-20 Years",
          "count": 2
        },
        {
          "range": "21+ Years",
          "count": 0
        }
      ]
    },
    {
      "company": "eBay",
      "totalJobs": 26,
      "distribution": [
        {
          "range": "0-3 Years",
          "count": 1
        },
        {
          "range": "4-6 Years",
          "count": 10
        },
        {
          "range": "7-9 Years",
          "count": 4
        },
        {
          "range": "10-12 Years",
          "count": 6
        },
        {
          "range": "13-16 Years",
          "count": 2
        },
        {
          "range": "17-20 Years",
          "count": 0
        },
        {
          "range": "21+ Years",
          "count": 1
        }
      ]
    }
  ],
  "dailyJobCounts": [
    {
      "date": "2025-11-11",
      "count": 371
    },
    {
      "date": "2025-11-12",
      "count": 384
    },
    {
      "date": "2025-11-13",
      "count": 325
    },
    {
      "date": "2025-11-14",
      "count": 416
    },
    {
      "date": "2025-11-15",
      "count": 310
    },
    {
      "date": "2025-11-16",
      "count": 215
    },
    {
      "date": "2025-11-17",
      "count": 494
    },
    {
      "date": "2025-11-18",
      "count": 447
    },
    {
      "date": "2025-11-19",
      "count": 608
    },
    {
      "date": "2025-11-20",
      "count": 555
    },
    {
      "date": "2025-11-21",
      "count": 488
    },
    {
      "date": "2025-11-22",
      "count": 255
    },
    {
      "date": "2025-11-23",
      "count": 310
    },
    {
      "date": "2025-11-24",
      "count": 1154
    },
    {
      "date": "2025-11-25",
      "count": 936
    },
    {
      "date": "2025-11-26",
      "count": 1057
    },
    {
      "date": "2025-11-27",
      "count": 891
    },
    {
      "date": "2025-11-28",
      "count": 937
    },
    {
      "date": "2025-11-29",
      "count": 696
    },
    {
      "date": "2025-11-30",
      "count": 568
    },
    {
      "date": "2025-12-01",
      "count": 1133
    },
    {
      "date": "2025-12-02",
      "count": 967
    },
    {
      "date": "2025-12-03",
      "count": 954
    },
    {
      "date": "2025-12-04",
      "count": 1081
    },
    {
      "date": "2025-12-05",
      "count": 1060
    },
    {
      "date": "2025-12-06",
      "count": 613
    },
    {
      "date": "2025-12-07",
      "count": 571
    },
    {
      "date": "2025-12-08",
      "count": 1234
    },
    {
      "date": "2025-12-09",
      "count": 980
    },
    {
      "date": "2025-12-10",
      "count": 1008
    },
    {
      "date": "2025-12-11",
      "count": 1000
    },
    {
      "date": "2025-12-12",
      "count": 995
    },
    {
      "date": "2025-12-13",
      "count": 644
    },
    {
      "date": "2025-12-14",
      "count": 547
    },
    {
      "date": "2025-12-15",
      "count": 1046
    },
    {
      "date": "2025-12-16",
      "count": 873
    },
    {
      "date": "2025-12-17",
      "count": 828
    },
    {
      "date": "2025-12-18",
      "count": 937
    },
    {
      "date": "2025-12-19",
      "count": 972
    }
  ],
  "experienceRanges": [
    "0-3 Years",
    "4-6 Years",
    "7-9 Years",
    "10-12 Years",
    "13-16 Years",
    "17-20 Years",
    "21+ Years"
  ],
  "totalCount": 4914
}